{"4qt9d": 5, "63htt": 1, "63k6t": 1, "63kd9": 5, "63kdc": 6, "63kdf": 1, "63kds": 1, "63ke4": 7, "63kec": 1, "63kjd": 3, "63kn3": 4, "63kn9": 8, "63knd": 3, "63th4": 3, "63th5": 2, "63thh": 6, "63tn2": 4, "63tn3": 33, "63tn6": 1, "63tnd": 1, "63vyn": 1, "66j8q": 4, "66j8t": 3, "66j8v": 1, "66j8w": 1, "66j8x": 5, "66j8z": 24, "66j9j": 45, "66j9k": 3, "66j9m": 36, "66j9p": 61, "66j9q": 13, "66j9r": 160, "66j9t": 5, "66j9w": 54, "66j9x": 119, "66j9y": 25, "66j9z": 20, "66jbb": 19, "66jbc": 3, "66jc0": 143, "66jc1": 76, "66jc2": 307, "66jc3": 28, "66jc4": 18, "66jc6": 52, "66jc7": 1, "66jc8": 51, "66jc9": 22, "66jcb": 32, "66jcc": 43, "66jcd": 30, "66jce": 10, "66jcf": 16, "66jdh": 1, "66jdp": 51, "66jf1": 1, "66jf5": 15, "66jf6": 3, "66jh5": 3, "66jhk": 2, "66jsk": 3, "66mx8": 1, "6knbp": 6, "6knbr": 16, "6kwnb": 11, "6mc5p": 1, "de2bw": 1, "sp6j0": 1, "u09wj": 1, "u2fkb": 1}