{"4qt99": 4, "4qt9d": 10, "63kdc": 9, "63kjf": 10, "63kn3": 3, "63kn9": 6, "63knd": 2, "63kne": 3, "63s4z": 1, "63swb": 1, "63th4": 1, "63tn2": 4, "63tn3": 8, "63tn5": 1, "63v8u": 1, "66j8y": 3, "66j8z": 4, "66j9h": 1, "66j9j": 11, "66j9m": 24, "66j9p": 27, "66j9q": 12, "66j9r": 16, "66j9t": 25, "66j9w": 28, "66j9x": 54, "66j9y": 16, "66j9z": 10, "66jbb": 20, "66jc0": 27, "66jc1": 16, "66jc2": 53, "66jc3": 77, "66jc4": 9, "66jc6": 29, "66jc8": 50, "66jc9": 29, "66jcb": 17, "66jcc": 28, "66jcd": 133, "66jce": 6, "66jcf": 12, "66jdp": 1, "66jdr": 1, "66jeb": 2, "66jek": 2, "66jem": 1, "66jf0": 13, "66jf4": 15, "66jf5": 11, "66jhk": 1, "66mx8": 1, "66t6h": 1, "69y7p": 1, "6knbr": 2, "6ktyz": 1, "wc2qg": 1}