{"6gysj": 1, "75bmp": 1, "75btm": 1, "75btx": 1, "75bv8": 1, "75bvg": 1, "75bvr": 3, "75bvx": 2, "75bvy": 1, "75bvz": 1, "75chb": 1, "75chf": 2, "75cj2": 2, "75cj4": 2, "75cj5": 2, "75cj8": 43, "75cj9": 1, "75cjb": 13, "75cjc": 1, "75cjf": 4, "75cjj": 1, "75cjn": 2, "75cjp": 1, "75cjs": 1, "75cjt": 1, "75cju": 2, "75cjv": 2, "75cjy": 1, "75cjz": 1, "75cm3": 2, "75cm8": 4, "75cm9": 11, "75cmf": 1, "75cnh": 1, "75cnk": 1, "75cnp": 1, "75cny": 1, "75cqh": 1, "7h024": 1, "7h428": 1, "7h4pq": 1, "7jswt": 1, "7nx1s": 1, "7nx1t": 1, "7nx4x": 1, "9qqts": 1, "eyfek": 1, "gcqzw": 1}