{"66mx8": 2, "69y7p": 1, "6f9xp": 1, "6fet4": 1, "6fews": 1, "6g7rs": 1, "6gkzq": 2, "6gm6z": 1, "6gmwb": 1, "6gxp9": 1, "6gycd": 1, "6gycg": 1, "6gyck": 1, "6gyf4": 11, "6gyft": 1, "6gyt8": 1, "6ukcs": 1, "6unfk": 1, "6utsk": 1, "6v0p7": 1, "6vb2s": 1, "6vjuf": 1, "6vjvd": 1, "6vjyj": 2, "6vjyn": 4, "6vsw1": 1, "6xmqd": 1, "6xx9h": 1, "6y433": 11, "6zqr4": 1, "6ztx8": 2, "6zvf0": 1, "75cjz": 1, "75cm0": 1, "75cm2": 1, "75cm3": 3, "75cm9": 4, "75cmc": 1, "75cn5": 1, "75cnn": 1, "7dmfp": 1, "7h40n": 1, "7jstu": 1, "7jswh": 1, "7jswk": 1, "7jswq": 1, "7jv11": 1, "7n3ss": 1, "7n8up": 1, "7nb6s": 1, "7nmbt": 1, "7nu29": 1, "7nve5": 1, "7nw75": 1, "7nx1v": 2, "7nx4j": 2, "7nx4m": 1, "7nxpr": 1, "7nyyx": 1, "7nyyy": 1, "7nyzn": 1, "7p1e1": 1, "7p1e4": 3, "7p5bb": 1, "7p5g1": 6, "7p5jk": 1, "7p6fg": 2, "7p6zq": 3, "7p771": 2, "7p774": 1, "7p7dw": 1, "7p7px": 1, "7p7py": 1, "7p7rf": 1, "7p7rx": 2, "7p7rz": 1, "7p7u5": 1, "7p7vy": 1, "7p7vz": 1, "7p7yn": 1, "7p83z": 1, "7p93t": 1, "7pe0j": 1, "7phft": 1, "7phfu": 1, "7phgp": 4, "7phgz": 1, "7php1": 2, "7phrf": 2, "7phw3": 1, "7phxe": 1, "7phzy": 1, "7pj6q": 1, "7pjb2": 1, "7pjmk": 1, "7pjne": 1, "7pjnq": 1, "7pjp0": 1, "7pjp4": 1, "7pk3z": 5, "7pk6q": 1, "7pk6x": 1, "7pk75": 1, "7pk7g": 3, "7pk7m": 1, "7pk7q": 5, "7pk7r": 3, "7pk7t": 2, "7pk86": 1, "7pk8s": 1, "7pk93": 2, "7pk99": 1, "7pk9b": 1, "7pk9c": 6, "7pk9g": 1, "7pk9q": 1, "7pk9u": 1, "7pk9v": 3, "7pk9w": 1, "7pk9x": 2, "7pk9y": 2, "7pk9z": 1, "7pkb3": 1, "7pkbk": 1, "7pkc0": 2, "7pkc4": 2, "7pkc9": 2, "7pkd0": 5, "7pkd1": 2, "7pkd3": 17, "7pkd4": 5, "7pkd5": 5, "7pkd6": 15, "7pkd7": 19, "7pkd8": 1, "7pkd9": 10, "7pkdb": 8, "7pkdc": 27, "7pkdd": 36, "7pkde": 73, "7pkdf": 34, "7pkdg": 1273, "7pkdh": 3, "7pkdk": 20, "7pkdn": 8, "7pkds": 39, "7pkdt": 8, "7pkdu": 52, "7pkhm": 1, "7pkhr": 1, "7pkhu": 1, "7pkhx": 1, "7pkjj": 2, "7pkk2": 1, "7pkk4": 1, "9q5ct": 1, "dp4dn": 1, "drdst": 1, "ezjmg": 1, "ezjq5": 1, "eztyj": 1, "gcpuv": 1, "gcpuy": 1, "qxhfm": 1, "sr2yk": 1, "sr3he": 1, "svc68": 1, "sy10z": 2, "ttnfv": 1, "u15d1": 1, "ucftp": 1, "w5g2q": 1, "xn76c": 1}