{"6rbnv": 1, "9eqhg": 1, "9fyp6": 1, "9g3my": 2, "9g3qv": 1, "9g3qw": 1, "9g3qz": 1, "9g3td": 1, "9g3w3": 1, "9g3w8": 6, "9g3wk": 1, "9g51n": 1, "9g6hm": 1, "9g6mg": 1, "9g756": 1, "9g77x": 1, "9g7cz": 1, "9g7p4": 1, "9g7se": 2, "9g7sf": 10, "9g7sg": 4, "9g7sr": 1, "9g7ss": 1, "9g7st": 34, "9g7su": 2, "9g7sv": 20, "9g7t4": 2, "9g7t5": 9, "9g7t6": 1, "9g7t7": 4, "9g7th": 556, "9g7tj": 1, "9ghnd": 1, "9gjyv": 1, "9t30t": 1, "9u8d7": 1, "9u8dj": 1, "d59mf": 1, "d5f0r": 1, "d7muk": 1, "dhj7t": 1, "dqcjq": 1, "eycs2": 1, "eysxc": 1, "gcncz": 1, "w649e": 1}