{"9mgzs": 2, "9mgzu": 1, "9mudj": 1, "9mup9": 1, "9mupd": 2, "9mupf": 1, "9q4s1": 1, "9q56m": 1, "9q59r": 2, "9q59x": 2, "9q5b7": 1, "9q5bc": 1, "9q5bf": 3, "9q5bg": 2, "9q5bu": 1, "9q5bv": 2, "9q5bz": 3, "9q5c0": 1, "9q5c1": 4, "9q5c2": 3, "9q5c3": 2, "9q5c4": 15, "9q5c5": 187, "9q5c6": 7, "9q5c7": 13, "9q5c8": 1, "9q5cb": 2, "9q5cc": 3, "9q5cd": 3, "9q5ce": 2, "9q5cf": 1, "9q5cg": 5, "9q5ch": 6, "9q5cj": 4, "9q5ck": 3, "9q5cm": 2, "9q5cn": 4, "9q5cp": 3, "9q5cq": 1, "9q5cr": 2, "9q5cs": 5, "9q5ct": 30, "9q5cu": 5, "9q5cv": 1, "9q5cw": 1, "9q5cz": 1, "9q5d0": 1, "9q5d2": 1, "9q5dw": 1, "9q5f4": 1, "9q5f5": 2, "9q5f6": 1, "9q5f8": 1, "9q5fh": 1, "9q5fj": 2, "9q5fm": 1, "9q5fn": 2, "9q5fq": 1, "9q5fr": 1, "9q5g8": 1, "9q8yy": 1, "9q9p1": 1, "9qce7": 1, "9qdck": 1, "9qh02": 2, "9qh05": 1, "9qh06": 2, "9qh0b": 3, "9qh0z": 1, "9qh10": 1, "9qh38": 1, "9qh3e": 2, "9qh3k": 1, "9qh3u": 1, "9qh6j": 1, "9qhh0": 1, "9qhh6": 1, "9qqj7": 1, "9qqjg": 1, "9v6kp": 1, "9vk1m": 1, "9z0gs": 1, "d42qf": 1, "dhwgt": 1, "djjd1": 1, "dn5bp": 1, "dnh02": 1, "dp3w5": 1, "dppn5": 1, "dqcjq": 1, "dr4e3": 1, "dr5rd": 1, "dr7fm": 1, "gcpvh": 1, "ke7fy": 1}