{"6utsk": 1, "6xmq4": 1, "6ztx8": 1, "9mupx": 1, "9muqd": 1, "9q5b9": 1, "9q5zb": 1, "9qhe8": 1, "9qmw2": 1, "9qmy2": 1, "9qqe4": 1, "9qqhb": 1, "9qqhc": 1, "9qqhd": 1, "9qqhg": 1, "9qqhu": 2, "9qqhw": 1, "9qqj0": 3, "9qqj2": 1, "9qqj6": 2, "9qqj7": 11, "9qqj9": 1, "9qqjc": 1, "9qqjd": 2, "9qqje": 8, "9qqjf": 2, "9qqjg": 22, "9qqjk": 69, "9qqjn": 1, "9qqjt": 2, "9qqju": 2, "9qqjv": 1, "9qqkw": 1, "9qqn2": 2, "9qqn3": 1, "9qqn5": 5, "9qqn6": 1, "9qxvr": 1, "9r4bc": 1, "9tbpp": 1, "9tbq3": 1, "9vg60": 1, "9vgq4": 1, "9vxzu": 1, "9w0w2": 1, "9yutj": 1, "9yuwd": 1, "9yw4c": 1, "c9fqx": 1, "djn44": 3, "dqbgy": 1, "dqcte": 1, "dqftx": 1, "eyck8": 1, "eye5k": 1, "eyesx": 1, "ez4h8": 1, "gc7x3": 1, "qpzqk": 1, "r6vjp": 1, "s2hjd": 1, "sp1b9": 1, "sp3e3": 1, "stq4r": 1, "sw6nf": 1, "tc1p9": 1, "te7v1": 1, "u1t0u": 1, "udtsf": 1, "w282d": 1}