{"9g3w8": 2, "9mueh": 1, "9q5cs": 1, "9qce7": 1, "9qdc6": 1, "9tbq3": 1, "9v6kp": 2, "9v7qp": 1, "9vfc0": 1, "9vfcj": 2, "9vfcv": 2, "9vfdp": 1, "9vffn": 1, "9vffu": 1, "9vffv": 1, "9vffz": 1, "9vfgp": 2, "9vfgs": 1, "9vfgy": 1, "9vfun": 4, "9vg13": 2, "9vg17": 1, "9vg1y": 1, "9vg45": 3, "9vg49": 2, "9vg4j": 1, "9vg4m": 6, "9vg4s": 2, "9vg4t": 1, "9vg5b": 40, "9vg5c": 1, "9vg5e": 2, "9vg5q": 4, "9vg5r": 3, "9vg5x": 1, "9vg5y": 2, "9vg5z": 2, "9vg7y": 1, "9vgh1": 1, "9vgh3": 1, "9vghd": 1, "9vghr": 1, "9xj64": 1, "9y4bj": 1, "9ygqf": 1, "9yju6": 1, "dn6tu": 1, "dp3r6": 1, "dp3wj": 2, "dpksf": 1, "drmrr": 1, "tf346": 1, "ttp43": 1, "u09t5": 1, "u0m71": 1, "u15mr": 1, "u6sce": 1, "wdw0b": 1, "wdw4d": 1, "wx4g0": 1}