{"9q5cp": 1, "9qc2h": 1, "9udem": 2, "9v4pf": 1, "9v60d": 1, "9v6kp": 1, "9v7bz": 1, "9v7c7": 3, "9v7cm": 1, "9v7cz": 1, "9v7qp": 1, "9v8vy": 3, "9vdpm": 1, "9vg4f": 1, "9vg5j": 1, "9vhrg": 2, "9vhrp": 1, "9vhrt": 2, "9vhwd": 1, "9vhwe": 1, "9vk00": 1, "9vk0h": 1, "9vk0s": 1, "9vk11": 1, "9vk15": 4, "9vk1f": 1, "9vk1h": 1, "9vk1j": 3, "9vk1m": 15, "9vk20": 1, "9vk22": 1, "9vk25": 52, "9vk2c": 1, "9vk2d": 1, "9vk2e": 2, "9vk2f": 1, "9vk2h": 2, "9vk2j": 5, "9vk37": 1, "9vk41": 1, "9vk57": 1, "9vk68": 2, "9vk9w": 1, "9vkdf": 1, "9vkh7": 1, "thrnh": 1}