{"9mupk": 16, "9muqc": 5, "9qbqs": 1, "9qh0m": 1, "9r92n": 1, "9v1zq": 1, "9v6kp": 1, "9vg4m": 1, "9vghs": 1, "9vk0f": 1, "9vk1m": 1, "9vzq0": 1, "9xj64": 1, "9xs7u": 1, "9xy3w": 1, "9y1by": 1, "9y69u": 3, "9ynms": 1, "9z1pf": 1, "9z2un": 16, "9z5rb": 3, "9z5z6": 1, "9z6g8": 2, "9z6xp": 5, "9z70p": 2, "9z70r": 29, "9z720": 4, "9z722": 2, "9z723": 1, "9z76w": 1, "9z77p": 3, "9z77s": 6, "9z77u": 1, "9z7cc": 2, "9z7de": 3, "9z7dg": 1, "9z7dj": 1, "9z7dk": 1, "9z7dm": 5, "9z7dn": 5, "9z7dq": 7, "9z7dr": 2, "9z7ds": 3, "9z7dw": 44, "9z7dx": 209, "9z7dy": 15, "9z7f2": 4, "9z7f7": 1, "9z7f8": 3, "9z7f9": 2, "9z7fb": 3, "9z7g0": 1, "9zk32": 1, "9zk7t": 1, "9zkh5": 1, "9zkhy": 2, "9zrs7": 1, "9zvxv": 2, "c20fb": 1, "dhvp5": 1, "dhwfx": 1, "dj6mh": 1, "djq5c": 1, "dnxhh": 1, "dnxsz": 5, "dpmuj": 2, "dqcjv": 1, "dqctf": 1, "dr5r7": 1, "drt2z": 1, "sv8wr": 1}