{"9q5ct": 1, "9r92h": 1, "9rb6x": 1, "9rbd8": 3, "9rbx8": 12, "9rbx9": 1, "9rcdr": 1, "9rcdx": 1, "9x23f": 1, "c206s": 1, "c206y": 1, "c208m": 2, "c2098": 1, "c209k": 1, "c20bf": 1, "c20d9": 1, "c20dc": 102, "c20df": 1, "c20dg": 5, "c20dh": 1, "c20dj": 2, "c20dn": 2, "c20dq": 2, "c20dt": 2, "c20du": 2, "c20e7": 1, "c20ej": 5, "c20ep": 3, "c20ey": 1, "c20f2": 2, "c20f4": 2, "c20f7": 1, "c20f9": 1, "c20fb": 74, "c20fs": 4, "c20fy": 1, "c20g6": 1, "c20g8": 7, "c20g9": 6, "c20gp": 2, "c20gs": 1, "c2143": 1}