{"9pz8q": 1, "9pzy0": 1, "9pzyb": 1, "9pzzf": 1, "9q5fh": 1, "9qbdx": 1, "9qdch": 1, "9qh11": 1, "9rf63": 1, "c0pb4": 1, "c0pvs": 1, "c0pzj": 1, "c203h": 1, "c203k": 1, "c206z": 1, "c209d": 1, "c209k": 1, "c209w": 1, "c20dg": 1, "c20dq": 1, "c20dx": 1, "c20eq": 2, "c20f3": 2, "c20fb": 13, "c20fc": 3, "c20ff": 1, "c20fg": 1, "c20fv": 1, "c20fy": 1, "c20g1": 1, "c20g4": 2, "c20g5": 1, "c20g6": 1, "c20g8": 14, "c20g9": 2, "c20gd": 114, "c20ge": 3, "c20gf": 1, "c20gg": 1, "c20gk": 2, "c20gs": 1, "c20sp": 1, "c20sz": 1, "c20ts": 1, "c20u2": 1, "c20u7": 2, "c20v2": 1, "c20vw": 1, "c20x5": 1, "c216n": 1, "c217f": 1, "c21ge": 1, "c21wg": 1, "c2286": 1, "c2295": 1, "c22zp": 1, "c23dh": 1, "c2wdp": 1, "dr558": 1, "drteu": 1, "q9gbf": 7, "tf340": 1, "w649g": 1}