{"9mv58": 1, "9qh0n": 1, "9tzwf": 1, "9v1s3": 1, "9v72g": 1, "9vg5n": 1, "9vu81": 1, "9wvmc": 1, "9xh9w": 1, "9xqq1": 1, "9xqq4": 1, "9xs7t": 1, "9z1rx": 1, "9ze3r": 1, "9zvwb": 1, "9zvx7": 2, "c22zp": 1, "c2xhe": 1, "c803s": 1, "c815b": 1, "c83g2": 1, "c8q6u": 2, "c8rfk": 1, "c8rzh": 1, "c8x4v": 1, "c8xfn": 1, "cb262": 1, "cb263": 1, "cb264": 1, "cb265": 2, "cb266": 24, "cb267": 1, "cb26c": 1, "cb2dm": 1, "cb2nt": 2, "cb3tb": 1, "cb4pe": 1, "cb4zj": 1, "cb6pt": 1, "cb74e": 1, "cb74k": 1, "cb74s": 4, "cb74t": 8, "cb97y": 1, "cbdbq": 1, "cbdbr": 4, "cbdyd": 1, "cbqnm": 1, "dhvr5": 1, "djn55": 1, "djz4s": 1, "dnfvw": 1, "dnq82": 1, "dp3wm": 1, "dqb0x": 1, "dr1yw": 1, "dr4u2": 1, "drmqu": 1, "drt2y": 1, "u4w19": 1}