{"9qh18": 1, "9zw3b": 1, "dhtud": 1, "dhtyd": 1, "dhv97": 1, "dhvjm": 1, "dhvjt": 2, "dhvjv": 1, "dhvjw": 2, "dhvjy": 1, "dhvjz": 8, "dhvk2": 1, "dhvmy": 1, "dhvn7": 2, "dhvnd": 1, "dhvne": 1, "dhvnj": 2, "dhvnk": 4, "dhvnm": 2, "dhvnn": 3, "dhvnp": 3, "dhvnq": 3, "dhvnr": 1, "dhvns": 3, "dhvnu": 25, "dhvnv": 2, "dhvnw": 1, "dhvnx": 1, "dhvp5": 5, "dhvph": 5, "dhvpj": 2, "dhvpk": 1, "dhvpm": 3, "dhvpn": 3, "dhvpq": 2, "dhvpr": 1, "dhvps": 1, "dhvpt": 1, "dhvpu": 1, "dhvpv": 1, "dhvpw": 1, "dhvqg": 3, "dhvqr": 1, "dhvr1": 1, "dhvr4": 1, "dhvr5": 3, "dhvrh": 1, "dhvwr": 1, "dhvx7": 1, "dhz1c": 1, "djj0h": 1, "djj1q": 1, "djj89": 1, "djj93": 1, "djjbn": 1, "djjk2": 1, "djjsj": 1, "djmut": 1, "djn4k": 1, "djq1q": 1, "dqcdg": 1, "dr7b9": 1}