{"62v9m": 1, "6q8d3": 1, "9q54y": 1, "9q59r": 1, "9tcs1": 1, "9vg5x": 1, "9vrfq": 1, "d9b3w": 1, "d9uhx": 1, "dhmgd": 2, "dhqk6": 1, "dhqy2": 1, "dhqzv": 1, "dhtud": 1, "dhvnk": 1, "dhwbb": 3, "dhwcg": 1, "dhwcu": 1, "dhwcv": 1, "dhwf0": 1, "dhwf6": 3, "dhwf7": 1, "dhwfe": 3, "dhwff": 2, "dhwfh": 1, "dhwfk": 2, "dhwfm": 1, "dhwfq": 4, "dhwfs": 3, "dhwft": 1, "dhwfw": 1, "dhwfx": 26, "dhwg1": 1, "dhwg7": 3, "dhwgc": 1, "dhwgf": 3, "dhwgg": 6, "dhwgh": 2, "dhwgk": 5, "dhwgn": 2, "dhwgp": 2, "dhwgr": 2, "dhwgs": 10, "dhwgt": 4, "dhwgu": 184, "dhwgv": 9, "dhwgw": 1, "dhwgy": 2, "dhwgz": 1, "dhwu5": 2, "dhwu6": 1, "dhwu7": 9, "dhwud": 1, "dhwuh": 4, "dhwuj": 1, "dhwuk": 1, "dhwum": 4, "dhwun": 2, "dhwup": 11, "dhwus": 1, "dhwut": 4, "dhwuv": 4, "dhwuw": 1, "dhwvj": 3, "dhwvp": 2, "dhwvq": 4, "dhwvr": 2, "dhwvt": 1, "dhx48": 4, "dhx4b": 3, "dhx52": 2, "dhx58": 6, "dhx5b": 3, "dhxh0": 4, "dhxh2": 2, "dhxh8": 7, "dhxh9": 1, "dhxhb": 1, "dhxhc": 1, "dhxj2": 2, "dhxj3": 1, "dhxj9": 1, "dhxjb": 2, "dhxn1": 1, "dhxp1": 1, "dhxp3": 2, "dhxp4": 1, "dhyg5": 1, "dhytv": 1, "dhz06": 1, "dhz0b": 1, "djjbn": 4, "djjk2": 1, "djmut": 1, "djq1w": 1, "djzzt": 1, "dn5ch": 1, "dngyk": 1, "dnh00": 1, "dnh0g": 1, "dnr1g": 1, "dnzbt": 1, "dp3t4": 1, "dqb0m": 1, "dqbvx": 1, "dqcjq": 3, "rjncd": 1, "sr628": 1, "u0psm": 1, "u0wmx": 1, "wdjeb": 1}