{"6dhue": 1, "75cm2": 1, "87z9q": 1, "9mudq": 1, "9q5cc": 1, "9q5ct": 1, "9q9k6": 1, "9q9qm": 1, "9q9v7": 1, "9qpyr": 1, "9tbq3": 1, "9v1zq": 1, "9vhwd": 1, "9vrfq": 2, "9w0w3": 1, "9x0xw": 1, "9xj65": 1, "9ykc7": 2, "9z0gs": 1, "9z7f9": 1, "c209c": 1, "c20fb": 1, "d2g64": 1, "dhqtv": 1, "dhtud": 1, "dhv2z": 1, "dhvjt": 1, "dhvk2": 2, "dhvnn": 1, "dhvqg": 1, "dhvqz": 1, "dhvrs": 1, "dhwc1": 2, "dhwf4": 1, "dhwfk": 1, "dhwfm": 1, "dhwfq": 1, "dhwfr": 1, "dhwfx": 20, "dhwfz": 2, "dhwgj": 1, "dhwgr": 1, "dhwgv": 1, "dhwu7": 1, "dhwum": 1, "dhwup": 2, "dhwut": 1, "dhwuv": 2, "dhwuw": 1, "dhwux": 1, "dhwuz": 1, "dhwvm": 1, "dhwvn": 2, "dhwvq": 1, "dhwvr": 1, "dhwvz": 1, "dhwyp": 1, "dhwzq": 3, "dhwzt": 7, "dhwzu": 1, "dhwzv": 2, "dhwzw": 1, "dhwzy": 3, "dhx48": 5, "dhx4b": 3, "dhx58": 7, "dhx59": 1, "dhx5b": 7, "dhxh0": 2, "dhxh8": 8, "dhxh9": 2, "dhxhb": 2, "dhxj0": 1, "dhxj1": 1, "dhxj2": 4, "dhxj3": 1, "dhxj8": 2, "dhxj9": 2, "dhxjc": 1, "dhxn0": 3, "dhxn1": 10, "dhxn3": 1, "dhxn8": 1, "dhxn9": 7, "dhxnb": 1, "dhxnc": 3, "dhxnf": 19, "dhxp0": 1, "dhxp1": 2, "dhxp2": 5, "dhxp3": 3, "dhxp4": 12, "dhxp6": 9, "dhxp8": 1, "dhxp9": 9, "dhxpb": 2, "dhxpc": 20, "dhxpd": 3, "dhxpf": 798, "dhyb7": 2, "dhybq": 1, "dhybv": 1, "dhyee": 1, "dhyft": 1, "dhyg5": 5, "dhyge": 1, "dhygn": 1, "dhyuh": 2, "dhyv6": 1, "dhyvf": 1, "dhz00": 1, "dhz01": 3, "dhz04": 7, "dhz06": 4, "dhz08": 7, "dhz09": 4, "dhz0c": 2, "dhz0d": 7, "dhz0f": 1, "dhz11": 6, "dhz13": 1, "dhz14": 1, "djjbn": 9, "djjcx": 1, "djjw4": 1, "djkj4": 2, "djm1w": 1, "djm2w": 2, "djmut": 3, "djn12": 1, "djn13": 1, "djn14": 1, "djn49": 1, "djn4k": 2, "djn9h": 1, "djn9j": 1, "djnd9": 1, "djnmn": 1, "djnqh": 2, "djwhg": 1, "djww0": 1, "djwx5": 1, "djzzt": 1, "dk8df": 2, "dn201": 1, "dn5bp": 2, "dnh7h": 1, "dnjqz": 1, "dnqyb": 1, "dnx83": 1, "dp3mv": 1, "dpmuh": 1, "dppqs": 1, "dq8vt": 1, "dq9cb": 1, "dqcmy": 1, "dqcqs": 1, "dr1sb": 1, "dr47p": 1, "dr4hy": 1, "dr4qf": 1, "dr4sx": 1, "dr5re": 2, "dr5rs": 3, "dr5ru": 2, "dr70y": 1, "dr72f": 1, "dr72j": 1, "dr72k": 1, "dr72r": 1, "dr7mm": 1, "drk24": 1, "drk8f": 1, "drk94": 1, "drkq4": 1, "drmqq": 4, "drms9": 1, "drq4u": 1, "drt5m": 1, "drt99": 1, "drtd1": 1, "dru8e": 1, "f241s": 1, "gcpvj": 2, "kpbpb": 1, "sr60k": 1, "sv9hc": 1, "u1516": 1, "u173z": 2, "ud9ys": 1}