{"9qqjg": 1, "9tbdm": 1, "9ypzx": 4, "9ypzy": 1, "djn5t": 1, "dn0p3": 1, "dn0p5": 1, "dn20h": 1, "dn20m": 1, "dn2fd": 2, "dn2gb": 1, "dn34n": 2, "dn34u": 1, "dn3bs": 1, "dn3v6": 1, "dn3zu": 1, "dn639": 1, "dn65m": 2, "dn67b": 1, "dn6ef": 2, "dn6jx": 1, "dn6kt": 1, "dn6kv": 1, "dn6m3": 1, "dn6m4": 2, "dn6m6": 1, "dn6m9": 8, "dn6mb": 1, "dn6md": 1, "dn6mg": 1, "dn6mz": 2, "dn6q0": 1, "dn6q1": 1, "dn6q5": 1, "dn6qd": 4, "dn6qn": 1, "dn6t9": 1, "dn6tu": 28, "dn6vu": 2, "dn6w5": 3, "dn6x0": 3, "dn7nj": 1, "dnd2v": 3, "dnk7c": 1, "dnkhc": 1, "dnkht": 1, "dnkkd": 1, "dnkks": 1, "dnmrc": 1, "dpsby": 1, "dr9ug": 1}