{"djvyu": 10, "djymk": 1, "djyrf": 1, "djyw8": 2, "djz4m": 1, "djz4s": 2, "djz4w": 1, "djz5e": 6, "djzh7": 2, "djzzs": 1, "dnjf3": 1, "dnjfy": 1, "dnjgp": 1, "dnjqp": 1, "dnjtt": 1, "dnjwz": 2, "dnn0z": 1, "dnn1r": 5, "dnn1z": 2, "dnn34": 3, "dnn36": 116, "dnn37": 11, "dnn39": 5, "dnn3b": 3, "dnn3c": 3, "dnn3j": 1, "dnn3k": 28, "dnn3m": 3, "dnn3n": 1, "dnn3r": 1, "dnn3s": 1, "dnn3w": 3, "dnn3y": 1, "dnn4m": 1, "dnn6n": 5, "dnn6p": 4, "dnn6r": 2, "dnn6t": 1, "dnn7d": 6, "dnn9z": 1, "dnnbe": 1, "dnnbg": 1, "dnnc4": 3, "dnnc9": 1, "dnnds": 1, "dnnsw": 3, "dnpec": 1, "dnq82": 2, "dqby8": 1}