{"9x0rd": 1, "9xj3j": 1, "dppn5": 1, "dpxff": 2, "dpxfg": 1, "dpxgh": 1, "dpxgq": 1, "dpxgv": 1, "dpxgx": 12, "dpxgy": 2, "dpxgz": 1, "dpxuj": 2, "dpxup": 2, "dpxuq": 1, "dpxur": 1, "dpxut": 1, "dpxux": 2, "dpxv1": 1, "dpxv3": 1, "dpxv4": 2, "dr4uz": 1, "dr5k2": 1, "dr5nb": 1, "dr5pg": 1, "dr5r8": 1, "dr5rk": 1, "dr70v": 1, "dr72m": 1, "dr81y": 1, "dr849": 1, "dr856": 1, "dr858": 1, "dr878": 1, "dr8h0": 1, "dr8hj": 1, "dr8hz": 1, "dr8k8": 1, "dr8kb": 1, "dr8q5": 1, "drddw": 1, "drdmn": 2, "dredb": 1, "dredd": 1, "drk4f": 1}