{"8e3rm": 1, "9q5cf": 1, "9q5ct": 2, "9q7m5": 1, "9q8yy": 1, "9qce7": 1, "9qh0k": 1, "9qh3f": 1, "9qqjg": 1, "9vg42": 1, "9vk1m": 2, "9vrfq": 2, "9wusb": 1, "9y69u": 1, "9zmkt": 1, "c23nb": 1, "d2kqe": 1, "d71qk": 3, "de30b": 1, "dhvqg": 1, "dhx4b": 1, "dj75d": 1, "djmut": 2, "djn1d": 1, "djn4u": 1, "djz4s": 1, "djzzt": 1, "dn5bp": 2, "dn78h": 1, "dng23": 1, "dnq7x": 1, "dnq82": 2, "dnruk": 1, "dnt5u": 1, "dnxhh": 1, "dnzft": 2, "dp73w": 1, "dp88v": 1, "dpj56": 1, "dpmuj": 2, "dppm1": 1, "dppn5": 1, "dpsbg": 1, "dpxuj": 2, "dq0vw": 1, "dq25d": 1, "dq2fx": 2, "dq2x7": 1, "dq3zf": 1, "dq6hr": 1, "dq6jj": 1, "dq6jn": 1, "dq6nf": 1, "dq8uv": 1, "dq8vm": 1, "dq8vt": 5, "dq8vu": 1, "dq92k": 2, "dq97z": 1, "dq989": 1, "dq98c": 8, "dq98s": 1, "dq99d": 1, "dq99k": 1, "dq99r": 1, "dq99w": 1, "dq99x": 4, "dq99y": 3, "dq99z": 1, "dq9bb": 11, "dq9bz": 1, "dq9c0": 15, "dq9c1": 5, "dq9c2": 1, "dq9c6": 3, "dq9c7": 2, "dq9c8": 28, "dq9cb": 2, "dq9cc": 1, "dq9cd": 6, "dq9ce": 11, "dq9cf": 1, "dq9cj": 3, "dq9ck": 8, "dq9cm": 1, "dq9cn": 1, "dq9cp": 1, "dq9cq": 3, "dq9cs": 3, "dq9ct": 6, "dq9cu": 4, "dq9cw": 8, "dq9cx": 438, "dq9cy": 2, "dq9d1": 1, "dq9df": 1, "dq9dg": 2, "dq9dp": 1, "dq9dt": 3, "dq9dw": 4, "dq9dx": 1, "dq9e3": 2, "dq9e5": 1, "dq9ef": 1, "dq9ep": 1, "dq9f1": 2, "dq9f5": 1, "dq9kn": 4, "dq9sd": 1, "dqb0q": 1, "dqbbf": 1, "dqbv1": 1, "dqbvq": 2, "dqby3": 1, "dqc4n": 1, "dqc5f": 1, "dqch6": 1, "dqche": 2, "dqchk": 1, "dqcjj": 1, "dqcjn": 1, "dqcjp": 1, "dqcjq": 8, "dqcjv": 1, "dqcm1": 1, "dqcnk": 1, "dqcq6": 1, "dqctb": 1, "dqcx8": 3, "dqcxc": 1, "dqd02": 1, "dqf28": 1, "dr460": 1, "dr47p": 1, "dr4e3": 2, "dr4e6": 1, "dr4h3": 1, "dr4kh": 1, "dr4sh": 1, "dr4x8": 1, "dr558": 1, "dr5re": 4, "dr5rm": 1, "dr5rs": 1, "dr79w": 1, "dr8v9": 1, "drk4g": 1, "drkep": 1, "drkk9": 1, "drq4e": 1, "drt2z": 2, "esb60": 1, "r22gb": 2, "r7hgd": 1, "u10j5": 1, "u1x0g": 1, "wh0qc": 1}