{"9wgzn": 1, "9xr1u": 1, "9y7tx": 1, "9yuwp": 1, "9z1xc": 1, "c2096": 1, "c2wdr": 1, "djjgb": 1, "dnh13": 3, "dnw2w": 1, "dnwdc": 1, "dnx81": 3, "dq8hf": 3, "dq8us": 1, "dq8v6": 2, "dq8v8": 2, "dq8ve": 2, "dq8vf": 2, "dq8vm": 1, "dq8vt": 2, "dq8vu": 2, "dq8y4": 1, "dq8y7": 1, "dq95c": 2, "dq9h1": 2, "dq9kn": 1, "dqbcm": 6, "dqbcv": 4, "dqbv7": 1, "dqch3": 1, "dqchc": 1, "dqcj5": 1, "dqcj7": 2, "dqcj8": 3, "dqcjv": 1, "dqcmq": 1, "dqcmv": 1, "dqcnj": 1, "dqcrh": 1, "dqcrm": 1, "dqcte": 1, "dqcw3": 1, "dqcw8": 1, "dr08m": 1, "dr0bx": 2, "dredb": 1, "drke4": 1, "f0k02": 1}