{"9q5c9": 1, "9q5ct": 1, "9qcsn": 1, "9tbqh": 1, "dhtz1": 1, "dhvjt": 1, "dq8vf": 1, "dqbuw": 1, "dqbvv": 1, "dqc79": 1, "dqc9b": 1, "dqcdh": 1, "dqcgk": 1, "dqchb": 1, "dqchx": 29, "dqchy": 1, "dqchz": 4, "dqcj3": 1, "dqcj5": 1, "dqcj6": 1, "dqcjj": 3, "dqcjn": 3, "dqcjp": 8, "dqcjq": 7, "dqcjr": 3, "dqcjv": 2, "dqcjw": 1, "dqcjx": 2, "dqckb": 4, "dqckc": 2, "dqckd": 2, "dqckg": 1, "dqcm0": 3, "dqcm1": 2, "dqcm2": 2, "dqcm3": 4, "dqcm4": 1, "dqcm5": 1, "dqcm6": 1, "dqcm9": 1, "dqcn1": 1, "dqcnj": 1, "dqcrw": 1, "dqcte": 1, "dqctf": 1, "dqctz": 1, "dqcv9": 1, "dqcw3": 1, "dqcx8": 1, "dr3b5": 1, "dr4ec": 1, "dr5re": 1, "dr5rx": 1, "dr63u": 2}