{"63hvk": 1, "9q5ct": 1, "9q5f5": 1, "9vk5c": 1, "9xqq1": 1, "dp0y2": 1, "dp6tj": 1, "dp94z": 1, "dppjd": 1, "dq9c8": 1, "dqcjm": 1, "dqcjq": 3, "dqcqq": 1, "dqcwb": 1, "dqcx8": 2, "dqfd5": 1, "dqfe4": 2, "dqfe7": 1, "dqfe9": 1, "dqfkr": 1, "dqfkw": 2, "dqfq6": 1, "dqfqc": 1, "dqfs2": 1, "dqfs3": 1, "dqfs4": 2, "dqfs5": 90, "dqfs7": 10, "dqfs9": 1, "dqfsb": 1, "dqfsd": 2, "dqfse": 1, "dr14d": 1, "dr185": 3, "dr1bu": 1, "dr1kf": 1, "dr1m6": 1, "dr41e": 1, "dr459": 1, "dr45k": 1, "dr460": 1, "dr4e1": 2, "dr4e2": 1, "dr4e3": 2, "dr4v6": 1, "dr558": 1, "dr5re": 2, "dr5ru": 1, "dr63c": 1, "dr72h": 1, "u12k4": 1}