{"9q5b3": 1, "dpp6m": 1, "dpp81": 1, "dq9cx": 1, "dqbmb": 1, "dqc8g": 1, "dqc9u": 1, "dqcht": 1, "dqchv": 1, "dqcmf": 1, "dqcmy": 1, "dqcqs": 2, "dqcrj": 1, "dqcrm": 1, "dqcrx": 1, "dqcte": 1, "dqcwb": 1, "dqcx0": 1, "dqcx1": 1, "dqcx5": 1, "dqcx8": 6, "dqcxg": 1, "dqcxu": 1, "dqcxv": 1, "dqf4p": 1, "dr0b1": 1, "dr0bm": 2, "dr12h": 1, "dr12p": 1, "dr12x": 22, "dr17m": 1, "dr17q": 2, "dr17r": 1, "dr181": 1, "dr188": 2, "dr18r": 1, "dr1b3": 2, "dr1b9": 1, "dr1dp": 1, "dr1e8": 1, "dr416": 1, "dr5ru": 2}