{"8e8x4": 1, "8e98n": 2, "9qh4h": 2, "9ufwp": 1, "cbk7h": 1, "djjtc": 1, "dnnx2": 4, "dp3wm": 1, "dp8fx": 3, "dqftx": 1, "dqfz1": 2, "dqfzj": 1, "dr41u": 1, "dr43f": 1, "dr46j": 3, "dr46m": 3, "dr46n": 38, "dr46r": 1, "dr47n": 1, "dr48h": 1, "dr48s": 2, "dr4bx": 1, "dr4d4": 2, "dr4dh": 1, "dr4dw": 1, "dr4e3": 7, "dr4e6": 1, "dr4ek": 3, "dr4ep": 1, "dr4ew": 1, "dr4g3": 3, "dr4g6": 1, "dr4gb": 5, "dr4j2": 1, "dr4kq": 1, "dr4mn": 1, "dr4ny": 2, "dr4nz": 1, "dr4qj": 1, "dr4t6": 1, "dr4u1": 1, "dr4u4": 6, "dr4u8": 1, "dr4uf": 3, "dr4uk": 1, "dr4ut": 3, "dr4vp": 1, "dr54z": 1, "dr55r": 2, "dr5hp": 1, "dr5j2": 2, "dr5j6": 1, "dr5j8": 1, "dr5jj": 1, "dr5jz": 1, "dr5k6": 2, "dr5ru": 1, "dr70t": 1, "dr721": 1, "dr72u": 1, "dr771": 1, "dr78c": 1, "dr79k": 1, "dr8vk": 1, "dredd": 1, "drg8h": 1, "drgey": 1}