{"9q5c2": 1, "9qqj7": 1, "9vfgp": 1, "9vrfq": 1, "9wup0": 1, "9xjdd": 1, "9xkgj": 1, "9zyjt": 1, "dhvr1": 1, "djfqv": 1, "djgzq": 2, "djn1t": 1, "djzzs": 1, "dn5bp": 2, "dnh0k": 1, "dnq2q": 1, "dnxrr": 1, "dp3qz": 1, "dpj59": 1, "dq9dw": 1, "dqcjn": 1, "dqcqz": 3, "dqfd5": 1, "dr1hz": 1, "dr1kc": 1, "dr1m4": 1, "dr1m7": 1, "dr1v8": 1, "dr46g": 1, "dr46z": 47, "dr47g": 1, "dr47j": 1, "dr47r": 1, "dr4d8": 1, "dr4db": 34, "dr4e1": 1, "dr4e3": 7, "dr4e4": 1, "dr4ef": 1, "dr4en": 1, "dr4kh": 2, "dr4me": 1, "dr4rz": 1, "dr4sb": 1, "dr4u0": 1, "dr5x0": 1, "dr726": 1, "thrru": 1, "u09yf": 1}