{"9muwu": 1, "9vz2h": 1, "9xduv": 1, "9z0gs": 1, "9zvbk": 1, "cbk9v": 1, "dje38": 1, "dncu0": 1, "dnm63": 2, "dpe6e": 1, "dppn5": 2, "dpr0t": 1, "dprp9": 2, "dqcjq": 1, "dqfe7": 1, "dr17q": 1, "dr1ez": 1, "dr1hv": 1, "dr1mp": 1, "dr1q8": 1, "dr1t0": 1, "dr1t6": 1, "dr1uh": 1, "dr347": 2, "dr465": 1, "dr46n": 2, "dr46s": 1, "dr47f": 1, "dr47r": 1, "dr4e3": 1, "dr4e6": 1, "dr4ek": 1, "dr4hy": 1, "dr4j2": 1, "dr4j3": 1, "dr4kr": 1, "dr4nw": 1, "dr4nx": 1, "dr4nz": 1, "dr4py": 1, "dr4pz": 1, "dr4qb": 1, "dr4qc": 1, "dr4qf": 13, "dr4qj": 1, "dr4qk": 1, "dr4qp": 2, "dr4qs": 1, "dr4qv": 3, "dr4r4": 1, "dr4r5": 5, "dr4r6": 1, "dr4r7": 1, "dr4rb": 1, "dr4rh": 145, "dr4rj": 8, "dr4rr": 2, "dr4rt": 1, "dr4ry": 1, "dr4sh": 1, "dr4sx": 1, "dr4uu": 1, "dr4x2": 4, "dr4x6": 2, "dr4z1": 1, "dr5rd": 1, "dr5re": 2, "dr5ru": 1, "dr60r": 1, "dr622": 1, "dr62n": 1, "dr690": 1, "dr6dr": 1, "dr6f0": 1, "dr6p2": 1, "dr70p": 1, "dr72j": 1, "dr73q": 1, "dr73x": 1, "dr7ee": 1, "dred9": 2, "drkh8": 1, "drt2z": 1, "drttj": 1, "kzf1p": 1, "sp36e": 1, "sw9kg": 1, "w2864": 1}