{"69y7n": 1, "6eyew": 1, "6gkzq": 1, "6gyf4": 1, "6msmj": 1, "6px5w": 1, "6r7ft": 1, "6y433": 1, "75cm9": 2, "7h2y8": 1, "7hdht": 1, "7p1df": 1, "87z9p": 1, "9mudj": 1, "9muf2": 1, "9muph": 1, "9muq6": 1, "9nzzx": 1, "9q59r": 1, "9q5bn": 1, "9q5bv": 2, "9q5c2": 2, "9q5c5": 2, "9q5c7": 1, "9q5cg": 1, "9q5cn": 1, "9q5ct": 17, "9q5d5": 1, "9q5ez": 1, "9q5f3": 1, "9q5f4": 1, "9q5f6": 2, "9q5f7": 1, "9q8yy": 1, "9q97b": 1, "9q9j5": 1, "9q9k6": 1, "9q9nu": 1, "9q9p1": 1, "9q9px": 1, "9q9ws": 1, "9qc0f": 1, "9qc0n": 1, "9qce7": 4, "9qcey": 1, "9qh1v": 1, "9qh2p": 1, "9qqhv": 1, "9qqje": 1, "9qqjg": 2, "9r5pz": 1, "9rtpq": 1, "9t9p6": 1, "9tbbt": 1, "9tbq3": 2, "9tbq9": 1, "9u89u": 1, "9udjq": 1, "9v1zq": 1, "9v6kp": 3, "9v8bk": 1, "9vbfq": 2, "9vffn": 1, "9vg4m": 3, "9vg5z": 1, "9vk1m": 4, "9vrfj": 1, "9vrfr": 1, "9vw86": 1, "9w0w2": 1, "9w8wu": 1, "9wdvz": 1, "9wunc": 1, "9x08w": 1, "9x0ry": 1, "9x0xq": 1, "9x23f": 1, "9xj65": 1, "9ygqf": 1, "9ypzy": 1, "9ypzz": 1, "9ywxz": 1, "9z0gs": 2, "9zvxv": 2, "c20fb": 4, "c20g6": 1, "c23jb": 1, "c23n8": 2, "c23nb": 4, "c2952": 1, "c2kzn": 1, "c3rmk": 1, "cb8ch": 1, "d1x7n": 2, "d59f9": 1, "d5dj6": 1, "d5f0r": 1, "d5f22": 1, "d71qh": 2, "d71qk": 2, "d7294": 3, "d7ksd": 1, "d7q31": 1, "d9uk8": 1, "ddmdu": 1, "ddme4": 1, "de0xy": 2, "de3bq": 1, "de56s": 1, "dhj7t": 1, "dhmgd": 1, "dhty0": 1, "dhvjz": 1, "dhvqf": 1, "dhvqg": 2, "dhvre": 1, "dhvzk": 1, "dhwf1": 1, "dhwfu": 1, "dhwfx": 7, "dhx4b": 4, "dhxh0": 1, "dhxj9": 1, "djfnq": 1, "djfq8": 2, "djjbn": 3, "djjcq": 1, "djjcx": 2, "djjgy": 1, "djn11": 1, "djn4k": 4, "djne0": 1, "dn4mb": 1, "dn5bp": 19, "dn5bt": 1, "dn5ch": 1, "dn6m9": 1, "dn9xq": 1, "dnet3": 1, "dng18": 4, "dnh10": 1, "dnh1x": 1, "dnk2t": 1, "dnkkd": 1, "dnnr5": 2, "dnq23": 1, "dnq82": 3, "dnq83": 1, "dny08": 3, "dp3qw": 1, "dp3tm": 1, "dp3tv": 1, "dp3ty": 1, "dp3w7": 1, "dp3wm": 4, "dpbm5": 1, "dpebr": 1, "dph1u": 1, "dpkkq": 1, "dpmg7": 1, "dpmuj": 1, "dpp6g": 1, "dpsby": 2, "dpsfg": 1, "dpt43": 1, "dpx2e": 1, "dpxgu": 1, "dpxuh": 1, "dpxuj": 1, "dpz83": 1, "dq0zh": 1, "dq25d": 1, "dq8vt": 2, "dq9cx": 2, "dq9eh": 1, "dqb1n": 1, "dqchs": 1, "dqcjq": 8, "dqck6": 1, "dqckf": 1, "dqcm0": 1, "dqcm8": 1, "dqcq7": 1, "dqcrz": 1, "dqcx8": 4, "dqfs5": 1, "dqfs9": 1, "dqfyc": 1, "dqfz0": 1, "dqgpf": 3, "dr2ch": 2, "dr3zx": 1, "dr460": 2, "dr4bp": 1, "dr4bq": 1, "dr4de": 2, "dr4df": 1, "dr4du": 1, "dr4dw": 1, "dr4e3": 5, "dr4e6": 3, "dr4e7": 1, "dr4j2": 1, "dr4kj": 1, "dr4m6": 1, "dr4r3": 1, "dr4uf": 4, "dr4vy": 1, "dr4yv": 2, "dr4yy": 2, "dr54z": 1, "dr558": 2, "dr55r": 2, "dr569": 1, "dr57g": 1, "dr5hp": 1, "dr5j8": 1, "dr5jg": 1, "dr5jm": 1, "dr5jy": 1, "dr5k4": 2, "dr5k6": 1, "dr5ku": 1, "dr5m5": 1, "dr5m7": 3, "dr5mh": 4, "dr5n3": 2, "dr5n6": 1, "dr5nc": 1, "dr5nd": 1, "dr5ng": 1, "dr5nj": 1, "dr5nm": 2, "dr5nn": 1, "dr5nq": 2, "dr5ns": 2, "dr5nu": 2, "dr5nw": 3, "dr5nx": 1, "dr5pj": 2, "dr5pm": 1, "dr5pp": 1, "dr5pq": 1, "dr5pr": 1, "dr5pv": 1, "dr5pw": 1, "dr5px": 2, "dr5pz": 1, "dr5qc": 3, "dr5qg": 1, "dr5qu": 26, "dr5qv": 10, "dr5qy": 8, "dr5qz": 7, "dr5r1": 3, "dr5r3": 1, "dr5r4": 14, "dr5r5": 20, "dr5r7": 6, "dr5r8": 8, "dr5rb": 1, "dr5rc": 1, "dr5rd": 4, "dr5re": 426, "dr5rg": 6, "dr5rh": 18, "dr5rj": 37, "dr5rk": 168, "dr5rm": 3278, "dr5rn": 26, "dr5rq": 40, "dr5rr": 18, "dr5rs": 109, "dr5rt": 107, "dr5ru": 125, "dr5rv": 49, "dr5rw": 20, "dr5rx": 38, "dr5ry": 15, "dr5rz": 15, "dr5wb": 2, "dr5wc": 2, "dr5wg": 1, "dr5wu": 1, "dr5wz": 1, "dr5x0": 6, "dr5x1": 1, "dr5x2": 5, "dr5x3": 5, "dr5x6": 1, "dr5x8": 25, "dr5x9": 1, "dr5xb": 5, "dr5xc": 10, "dr5xd": 5, "dr5xf": 1, "dr5xg": 5, "dr5xh": 2, "dr5xj": 1, "dr5xk": 1, "dr5xm": 1, "dr5xn": 1, "dr5xs": 2, "dr5xv": 1, "dr5xx": 1, "dr5xy": 1, "dr5xz": 4, "dr5z3": 1, "dr5z6": 1, "dr5z9": 1, "dr5zr": 1, "dr5zs": 1, "dr5zv": 1, "dr61w": 1, "dr62g": 1, "dr63v": 1, "dr65w": 1, "dr66j": 1, "dr6b7": 2, "dr6be": 1, "dr6bw": 1, "dr6bx": 1, "dr6cu": 1, "dr6gk": 2, "dr6rc": 1, "dr6vr": 2, "dr6wh": 1, "dr6wx": 1, "dr6y3": 1, "dr701": 2, "dr70t": 1, "dr70w": 1, "dr718": 2, "dr71j": 1, "dr722": 1, "dr725": 3, "dr727": 1, "dr72b": 4, "dr72e": 1, "dr72f": 1, "dr72h": 16, "dr72j": 53, "dr72k": 3, "dr72m": 39, "dr72n": 3, "dr72p": 3, "dr72q": 10, "dr72r": 43, "dr72w": 18, "dr72x": 18, "dr72y": 5, "dr72z": 4, "dr733": 1, "dr734": 1, "dr73b": 1, "dr73g": 1, "dr73q": 1, "dr73u": 3, "dr73v": 1, "dr73x": 3, "dr74v": 1, "dr751": 1, "dr75g": 3, "dr75p": 1, "dr764": 1, "dr76h": 1, "dr76k": 1, "dr77m": 1, "dr77t": 1, "dr780": 4, "dr781": 1, "dr782": 9, "dr784": 1, "dr788": 3, "dr789": 1, "dr78b": 4, "dr78f": 1, "dr78h": 1, "dr792": 2, "dr793": 1, "dr794": 1, "dr795": 1, "dr796": 1, "dr798": 1, "dr79b": 1, "dr79q": 1, "dr79w": 4, "dr7b0": 1, "dr7b5": 1, "dr7bj": 1, "dr7db": 1, "dr7dc": 1, "dr7et": 1, "dr7fh": 2, "dr7fj": 1, "dr7fr": 1, "dr7g2": 1, "dr7g3": 1, "dr7h0": 1, "dr7hp": 1, "dr7jq": 1, "dr7jt": 1, "dr7k5": 1, "dr7k6": 1, "dr7kw": 1, "dr7md": 2, "dr7p9": 1, "dr7q7": 1, "dr7r1": 1, "dr7r4": 1, "dr7rq": 1, "dr7sm": 1, "dr7xz": 1, "dr86w": 1, "dr8h7": 1, "dr8mb": 1, "dr8sf": 1, "dr8sx": 1, "dr8uc": 1, "dr8ug": 1, "dr8v1": 1, "dr8v8": 1, "dr8v9": 1, "dr8vg": 1, "dr906": 1, "dr997": 1, "dr9uu": 1, "dr9ve": 1, "dr9y5": 1, "drdmf": 1, "drdst": 5, "dre2q": 1, "dre2z": 1, "dre6v": 2, "dre7s": 1, "dre7t": 1, "dre82": 1, "dred9": 4, "dredt": 1, "dree3": 2, "dree5": 1, "drehp": 1, "drej5": 1, "dres0": 1, "drew7": 1, "drewe": 1, "drg83": 1, "drge1": 1, "drguw": 1, "drgv2": 1, "drgvj": 1, "drhpf": 1, "drk05": 2, "drk0b": 1, "drk0j": 2, "drk0r": 2, "drk2b": 1, "drk2g": 1, "drk42": 2, "drk49": 1, "drk4u": 3, "drk5m": 2, "drk88": 3, "drk94": 2, "drk9j": 1, "drk9k": 1, "drkc6": 5, "drkcd": 2, "drkce": 1, "drkg1": 1, "drkgp": 1, "drkh6": 1, "drkhz": 1, "drkjj": 1, "drkjp": 2, "drkkb": 1, "drkm9": 1, "drkmd": 2, "drkme": 2, "drkmy": 1, "drks6": 1, "drksp": 1, "drksr": 1, "drkw8": 1, "drmr6": 1, "drqp4": 2, "drt2t": 1, "drt2u": 1, "drt2y": 1, "drt2z": 3, "drt37": 1, "drt3p": 1, "drt41": 1, "drt69": 1, "drtjj": 1, "drtmz": 1, "drtrg": 1, "dru75": 8, "drv2c": 1, "drvtj": 1, "ez99y": 1, "ezjmf": 1, "ezjmu": 1, "ezwyf": 1, "f257y": 1, "f25b4": 1, "gc0yz": 1, "gc3be": 1, "gc7x3": 1, "gcjjn": 1, "gcput": 1, "gcpuv": 1, "gcpuy": 2, "gcpvh": 5, "gcpvj": 9, "gcqfj": 1, "gcrbp": 1, "gcvy2": 1, "gcybg": 1, "kekj6": 1, "ksf6k": 1, "kygcj": 1, "qd67c": 1, "qqwhn": 1, "rcm38": 1, "s11zg": 1, "s14kw": 1, "s2hjd": 1, "s9rzr": 1, "sdz0w": 1, "snx3g": 1, "sp91f": 1, "spqse": 1, "spzpg": 1, "sr4tk": 1, "sr8n9": 1, "sr8s9": 1, "srfm6": 1, "sx1r2": 1, "sxk60": 1, "tc0z1": 3, "tewz2": 2, "tf340": 1, "thrr3": 1, "ttnfu": 1, "ttwem": 1, "tue00": 1, "u09tu": 1, "u09tv": 3, "u0frv": 1, "u0hs6": 1, "u0nd9": 1, "u0ngg": 1, "u0u65": 1, "u0ws6": 1, "u0yjj": 1, "u10jw": 1, "u155n": 1, "u1p45": 1, "u2jc3": 1, "u336x": 1, "u33db": 1, "u4gzr": 1, "u9ed3": 1, "ucfv0": 1, "ud1hh": 1, "vc7rp": 1, "w0whm": 1, "w4rw2": 1, "w9zhv": 1, "wc8x9": 1, "wdp2r": 1, "wdw4f": 1, "ws4kp": 1, "xn3z4": 1, "xn76g": 1}