{"6fgbf": 1, "75cm9": 1, "9g37t": 1, "9q5c4": 1, "9q5du": 1, "9zzdh": 1, "c23nb": 1, "c27hj": 1, "c815b": 1, "djjbn": 1, "dnh0q": 1, "dp3wg": 1, "dpcdu": 1, "dpxue": 1, "dqfxt": 1, "dqfz0": 1, "dqfzq": 1, "dr46m": 1, "dr49x": 1, "dr4de": 1, "dr4dk": 1, "dr4e3": 1, "dr4er": 1, "dr4u4": 1, "dr4vp": 1, "dr4zj": 1, "dr5m7": 1, "dr5nf": 1, "dr5nm": 1, "dr5nv": 1, "dr5pj": 1, "dr5pn": 1, "dr5pp": 2, "dr5ps": 1, "dr5pw": 2, "dr5px": 1, "dr5py": 1, "dr5q9": 1, "dr5qc": 1, "dr5qt": 1, "dr5qu": 4, "dr5qy": 3, "dr5qz": 1, "dr5r1": 2, "dr5r4": 3, "dr5r5": 6, "dr5r7": 1, "dr5r8": 2, "dr5r9": 1, "dr5rc": 1, "dr5re": 12, "dr5rg": 1, "dr5rh": 113, "dr5rj": 3, "dr5rk": 19, "dr5rm": 19, "dr5rq": 10, "dr5rr": 1, "dr5rs": 12, "dr5rt": 6, "dr5ru": 28, "dr5rv": 6, "dr5rw": 1, "dr5rx": 18, "dr5ry": 7, "dr5rz": 6, "dr5x2": 2, "dr5x3": 3, "dr5x8": 10, "dr5xd": 1, "dr5xf": 2, "dr5xu": 1, "dr5z3": 1, "dr5z8": 1, "dr5ze": 1, "dr6b3": 1, "dr6bt": 1, "dr6bw": 1, "dr6gk": 1, "dr708": 1, "dr70x": 2, "dr720": 1, "dr721": 1, "dr725": 1, "dr726": 1, "dr72e": 1, "dr72j": 11, "dr72k": 2, "dr72m": 14, "dr72n": 3, "dr72p": 1, "dr72q": 6, "dr72r": 5, "dr72s": 1, "dr72w": 8, "dr72x": 1, "dr768": 1, "dr773": 1, "dr782": 1, "dr793": 1, "dr795": 1, "dr7b0": 1, "dr7bs": 1, "dr7cc": 1, "dr7cu": 1, "dr7de": 1, "dr7f4": 1, "dr7gd": 1, "dr7k5": 1, "dr8ux": 1, "dr8v1": 1, "dr9v9": 1, "dre7e": 1, "dre82": 1, "drg44": 1, "drgvj": 1, "drhpb": 1, "drhpd": 1, "drk08": 1, "drk0c": 1, "drk4u": 1, "drkcd": 1, "drkeq": 1, "drkkh": 1, "drkmd": 1, "drkn3": 1, "drt2y": 1, "dry8y": 1, "gbx7x": 1, "gcpvh": 1, "kzf0t": 1, "r3gx4": 1, "ttp4f": 1, "u09tv": 1}