{"dpx2e": 2, "dpx2s": 2, "dpxf3": 1, "dpxgv": 1, "dpxgw": 1, "dpxgz": 1, "dpxu9": 2, "dpxue": 1, "dpxup": 1, "dpxux": 2, "dpxvm": 1, "dr4bv": 1, "dr4e4": 1, "dr4vm": 1, "dr4vw": 2, "dr568": 1, "dr570": 2, "dr5kb": 1, "dr5nt": 1, "dr5pw": 1, "dr5r5": 1, "dr5r7": 2, "dr5r8": 1, "dr5re": 2, "dr5rf": 1, "dr5rk": 1, "dr5ru": 2, "dr5x8": 1, "dr6b3": 1, "dr70k": 1, "dr70t": 1, "dr721": 1, "dr726": 1, "dr72z": 2, "dr767": 1, "dr78p": 1, "dr7kd": 1, "dr7kw": 1, "dr86j": 6, "dr86q": 3, "dr86w": 5, "dr86y": 10, "dr872": 4, "dr878": 10, "dr87f": 32, "dr8d0": 4, "dr8e1": 2, "dr8eb": 13, "dr8hm": 1, "dr8hw": 1, "dr8k1": 1, "dr8k4": 1, "dr8kj": 1, "dr8ks": 2, "dr8kt": 1, "dr8m0": 3, "dr8mu": 3, "dr8qn": 2, "dr8s2": 2, "dr8sw": 1, "dr8uf": 1, "dr8v2": 1, "dr8v8": 3, "dr8ve": 1, "dr9hv": 1, "dr9k2": 1, "dr9uv": 1, "drd76": 1, "drdmn": 1, "drdux": 1, "drdv6": 1, "dre6v": 1, "dre74": 1, "dred5": 1, "dred9": 1, "dreh7": 1, "drehu": 1, "dres1": 1, "drkkw": 1}