{"9t947": 1, "9ymnb": 1, "9z7f9": 1, "dpxgj": 1, "dqfyc": 1, "dr2pr": 1, "dr4df": 1, "dr4dg": 2, "dr4dy": 1, "dr4er": 1, "dr4ue": 1, "dr4uf": 1, "dr5hy": 1, "dr5kf": 1, "dr5ns": 1, "dr5nt": 1, "dr5pj": 2, "dr5py": 1, "dr5r5": 1, "dr5r8": 1, "dr5rj": 1, "dr5rk": 1, "dr5rm": 1, "dr5rn": 1, "dr5ru": 5, "dr5rw": 1, "dr5rx": 1, "dr5ry": 1, "dr5xc": 1, "dr6tq": 1, "dr72p": 1, "dr72x": 1, "dr77h": 1, "dr77j": 1, "dr782": 1, "dr788": 1, "dr78n": 1, "dr79x": 1, "dr7b3": 1, "dr7eb": 1, "dr7s2": 1, "dr8mb": 1, "dr8qh": 1, "dr8v8": 1, "dr8w9": 1, "dr94c": 1, "dr9kz": 1, "dr9ug": 1, "drdup": 1, "drdux": 1, "drdw1": 1, "dre6z": 4, "dre77": 1, "dre7e": 1, "dre7j": 1, "dre7m": 2, "dre7n": 1, "dre94": 1, "dre9b": 1, "dre9x": 2, "dred6": 1, "dred9": 1, "dredb": 2, "dredc": 4, "dredd": 7, "dredf": 3, "dredg": 1, "dreds": 1, "dree0": 4, "dree1": 4, "dree3": 1, "dree4": 19, "dree9": 2, "dreec": 3, "dreed": 1, "dreeh": 1, "dregg": 1, "dreh0": 1, "drehj": 1, "drehn": 1, "drehu": 1, "drekr": 1, "dremb": 1, "dres0": 4, "dres1": 1, "dres2": 1, "dresp": 1, "dret1": 2, "dretd": 3, "drewh": 1, "drg4p": 1, "drgb3": 1, "drgf2": 1, "drkm6": 1}