{"djg94": 1, "dp3x8": 1, "dppp4": 1, "drkg0": 1, "drkgy": 1, "drkjn": 1, "drkk9": 1, "drkkn": 1, "drkvm": 1, "drm5s": 1, "drm7c": 1, "drmhg": 2, "drmj5": 1, "drmjj": 3, "drmjq": 1, "drmjw": 1, "drmjy": 7, "drmk0": 1, "drmk1": 2, "drmkf": 1, "drmmb": 3, "drmme": 1, "drmn7": 1, "drmn9": 1, "drmng": 1, "drmnh": 1, "drmnk": 1, "drmnp": 3, "drmnr": 1, "drmnt": 7, "drmnv": 2, "drmnz": 2, "drmpy": 1, "drmq0": 1, "drmq2": 1, "drmqq": 2, "drmxn": 1, "drt0s": 1, "drt2p": 2, "drt2u": 1, "drt2z": 2, "drt3j": 1}