{"9g3mz": 2, "9g3qh": 3, "9g3qk": 1, "9g3qq": 1, "9g3qr": 4, "9g3qw": 1, "9g3qx": 1, "9g3qz": 1, "9g3t9": 2, "9g3tc": 1, "9g3w2": 1, "9g3w3": 1, "9g3w8": 1, "gbuj1": 1, "gbvw8": 1, "gbwqr": 1, "gbwrv": 1, "gbwry": 3, "gbwrz": 392, "gbww8": 1, "gbwx8": 1, "gbwxb": 14, "gbwxf": 1, "gby15": 1, "gby1m": 1, "gby2h": 1, "gby2j": 2, "gby2n": 1, "gby80": 1, "gby81": 1, "gcey9": 1, "gcjb6": 6, "gcjgj": 2, "gcjuj": 2, "gcjvb": 2, "gcmze": 1, "gcnge": 1, "gcnhk": 2, "gcnhn": 1, "gcnjj": 1, "gcnk1": 1, "gcnqs": 1, "gcnqu": 1, "gcp0y": 2, "gcp0z": 3, "gcp1n": 1, "gcp1p": 2, "gcp46": 1, "gcp8c": 1, "gcp9h": 1, "gcpf8": 1, "gcpje": 4, "gcpjs": 1, "gcpk8": 1, "gcpkj": 1, "gcpkr": 6, "gcpnf": 2, "gcpsq": 3, "gcpsr": 2, "gcpss": 1, "gcpst": 1, "gcpsx": 3, "gcpsz": 4, "gcpt4": 2, "gcptm": 1, "gcptr": 1, "gcptw": 1, "gcpu7": 1, "gcpu8": 3, "gcpub": 1, "gcpud": 1, "gcpue": 2, "gcpuf": 3, "gcpuh": 2, "gcpum": 1, "gcpuq": 1, "gcpus": 3, "gcput": 1, "gcpuv": 7, "gcpuw": 2, "gcpuy": 5, "gcpv0": 3, "gcpv4": 2, "gcpv5": 2, "gcpv6": 1, "gcpv7": 2, "gcpvd": 1, "gcpve": 1, "gcpvh": 1, "gcpvj": 10, "gcpvk": 3, "gcpvm": 6, "gcpvn": 17, "gcpvp": 4, "gcpvq": 1, "gcpvr": 6, "gcpvw": 5, "gcpy2": 1, "gcpyn": 3, "gcpyp": 1, "gcpyx": 1, "gcpz7": 1, "gcq3g": 1, "gcq8j": 2, "gcqc7": 1, "gcqd5": 2, "gcqde": 1, "gcqdn": 2, "gcqey": 2, "gcqny": 1, "gcqq0": 2, "gcqrg": 1, "gcquz": 1, "gcqzt": 2, "gcqzw": 1, "gcr5q": 1, "gcrb6": 1, "gcrj9": 1, "gcvjb": 1, "gcvjd": 1, "gcvwr": 1, "gcw0w": 1, "gcw2d": 1, "gcw2h": 1, "gcw2j": 1, "gcwfh": 1, "gcwgm": 1, "gcx4z": 1, "gcx9w": 3, "gcx9x": 4, "gcx9z": 9, "gcxf0": 1, "gcyc5": 1, "gfjch": 1, "sp95g": 1, "tsvck": 1, "u100v": 1, "u107e": 1, "u10h6": 8, "u10h8": 1, "u10h9": 2, "u10hb": 1, "u10hg": 1, "u10j0": 2, "u10j1": 1, "u10j3": 1, "u10j8": 8, "u10jh": 1, "u10q6": 1, "u128j": 2, "u12gm": 3, "u12nr": 3, "u6s89": 2, "u6sc8": 1, "u6scc": 1, "u6sce": 3, "w21z6": 1, "w21zb": 2, "w21zc": 3, "w21ze": 2, "w21zg": 1, "w21zt": 2, "w23b4": 1, "wdw4c": 1}