{"9g3je": 2, "9g3qr": 2, "9g3qx": 2, "9g3qy": 1, "9g3rm": 1, "9g3w8": 1, "9g3wc": 1, "9q9hq": 1, "9s7th": 1, "d2g60": 1, "eyckr": 1, "gbvnd": 1, "gbwrz": 1, "gbwxb": 4, "gby1t": 1, "gcjub": 1, "gcmzu": 2, "gcn5j": 1, "gcnrj": 1, "gcp0y": 4, "gcp0z": 1, "gcp1p": 2, "gcpcj": 1, "gcpef": 1, "gcpfg": 2, "gcpk8": 1, "gcpk9": 1, "gcpmp": 1, "gcpnk": 1, "gcpsc": 1, "gcpsj": 1, "gcpsn": 1, "gcpsq": 1, "gcpsr": 3, "gcpss": 1, "gcpst": 7, "gcpsw": 150, "gcpsx": 4, "gcpsz": 1, "gcpu3": 1, "gcpu7": 2, "gcpu8": 1, "gcpub": 1, "gcpuc": 2, "gcpue": 2, "gcpuf": 1, "gcpug": 3, "gcpus": 1, "gcpuu": 4, "gcpuv": 1, "gcpuy": 1, "gcpuz": 2, "gcpv0": 1, "gcpv2": 1, "gcpv5": 1, "gcpv7": 2, "gcpvd": 1, "gcpve": 3, "gcpvg": 1, "gcpvh": 2, "gcpvj": 6, "gcpvk": 2, "gcpvm": 8, "gcpvn": 8, "gcpvp": 1, "gcpvq": 1, "gcpvs": 2, "gcpvx": 1, "gcpwz": 1, "gcpxv": 1, "gcpy2": 1, "gcpyp": 2, "gcq6h": 1, "gcqdh": 1, "gcqey": 3, "gcqf8": 5, "gcqny": 1, "gcr1m": 1, "gcuvy": 1, "gcvnj": 1, "gcvwq": 1, "gcw0w": 1, "gcw27": 1, "gcw2h": 1, "gcw2j": 1, "gcwfh": 1, "gcwvv": 1, "gcxcb": 1, "r1qbe": 2, "u100c": 1, "u1042": 1, "u104v": 1, "u10dg": 2, "u10du": 1, "u10h3": 1, "u10h6": 2, "u10h9": 1, "u10hb": 1, "u10he": 1, "u10j0": 2, "u10j1": 1, "u10j8": 2, "u10mq": 1, "u10q6": 1, "u10xh": 1, "u1215": 3, "u128j": 3, "u12gm": 2, "u12uv": 1, "u6scb": 1, "u6scc": 2, "u6sce": 3, "w21xx": 1, "w21z3": 1, "w21z6": 2, "w21z9": 1, "w21zc": 1, "w21zf": 1, "w21zs": 1, "w21zt": 1, "w23b1": 1}