{"7zzxz": 1, "9g3qn": 2, "9g3qq": 1, "9g3qr": 3, "9g3qy": 1, "9g3t8": 1, "9g3w2": 2, "9g3w6": 1, "9g3w9": 2, "9g3wc": 2, "dpz83": 3, "dr5ru": 1, "gbwrz": 3, "gbwxb": 1, "gbwxf": 1, "gby1k": 1, "gby2j": 1, "gcj88": 1, "gcjfu": 1, "gcjsx": 1, "gcjub": 2, "gcmzu": 3, "gcn5j": 1, "gcnht": 1, "gcnk6": 1, "gcp0y": 6, "gcpch": 6, "gcpcj": 1, "gcpeg": 1, "gcpjf": 1, "gcpk8": 3, "gcpkt": 1, "gcpmp": 1, "gcpmy": 1, "gcpry": 2, "gcpsw": 1, "gcpsx": 4, "gcpsy": 1, "gcpsz": 241, "gcpt1": 1, "gcptj": 1, "gcpu7": 1, "gcpu9": 1, "gcpub": 2, "gcpuc": 1, "gcpud": 2, "gcpue": 2, "gcpuf": 3, "gcpug": 3, "gcpuh": 1, "gcpus": 2, "gcpuv": 3, "gcpux": 1, "gcpuy": 10, "gcpuz": 1, "gcpv0": 1, "gcpv1": 2, "gcpv4": 2, "gcpv5": 2, "gcpv6": 3, "gcpve": 1, "gcpvj": 15, "gcpvm": 6, "gcpvn": 8, "gcpvp": 2, "gcpvq": 1, "gcpvr": 2, "gcpvt": 1, "gcpvx": 1, "gcpyp": 2, "gcqcm": 1, "gcqd5": 3, "gcqdh": 1, "gcqds": 3, "gcqrv": 1, "gcquh": 1, "gcqvn": 1, "gcqzt": 1, "gctbh": 2, "gcuvf": 1, "gcvnj": 1, "gcw2h": 2, "gcw2n": 1, "gcw2q": 1, "gcwfh": 2, "gcxcb": 1, "gcy0y": 1, "gfnt0": 5, "sqg0u": 1, "tsjbv": 1, "ttnff": 1, "u104v": 1, "u104y": 1, "u107e": 1, "u10dv": 1, "u10g8": 1, "u10gc": 1, "u10h2": 1, "u10h6": 6, "u10h8": 1, "u10h9": 1, "u10j0": 1, "u10j8": 2, "u10px": 1, "u10q6": 1, "u10s0": 2, "u10xj": 1, "u120g": 2, "u1214": 3, "u12gk": 1, "u6sc9": 3, "u6scb": 1, "u6scd": 1, "w21z8": 2, "w21zc": 1, "w21ze": 1, "w21zg": 1, "w21zk": 1, "w23b1": 1, "w23b4": 3}