{"9g3qr": 1, "dnzbe": 1, "gbwxb": 1, "gc7xk": 1, "gcnhg": 1, "gcp0y": 1, "gcpdy": 1, "gcpke": 1, "gcpkr": 1, "gcpmn": 1, "gcpqx": 2, "gcpsv": 1, "gcpsw": 1, "gcpsx": 2, "gcpt5": 1, "gcptn": 1, "gcptp": 2, "gcptq": 1, "gcptr": 1, "gcptu": 1, "gcpty": 1, "gcpu9": 1, "gcpuf": 1, "gcpus": 1, "gcpuy": 1, "gcpv0": 1, "gcpv2": 40, "gcpv3": 2, "gcpv4": 1, "gcpv5": 1, "gcpv7": 1, "gcpv8": 2, "gcpvh": 1, "gcpvj": 14, "gcpvn": 1, "gcpvq": 1, "gcpyp": 1, "gcqde": 1, "gcqt2": 1, "gcw2m": 1, "gcwfn": 1, "gcx9z": 1, "gcxcb": 1, "sb4fm": 1, "u037m": 1, "u0bc3": 1, "u107g": 1, "u10j8": 1, "u12gt": 1, "w21zt": 1}