{"9g3qn": 1, "9g3rn": 1, "9g3tc": 1, "9g3w7": 1, "9q8yy": 1, "dhwfx": 1, "dnkee": 1, "dqcjp": 1, "dr8hm": 1, "drmwx": 1, "eyt0y": 1, "ez3f5": 1, "ezp8x": 1, "f08u7": 1, "gc7x3": 1, "gcdd2": 1, "gcetv": 1, "gceyd": 1, "gcfg0": 1, "gcmzt": 1, "gcmzu": 1, "gcn44": 2, "gcn8s": 1, "gcn8t": 1, "gcnht": 1, "gcnhy": 1, "gcpcj": 4, "gcpef": 2, "gcpnf": 1, "gcpsm": 1, "gcpsx": 1, "gcpsy": 1, "gcptj": 1, "gcptr": 2, "gcpu8": 1, "gcpub": 1, "gcpuf": 1, "gcpug": 1, "gcpuq": 1, "gcpuu": 3, "gcpuv": 3, "gcpuy": 1, "gcpvh": 1, "gcpvj": 9, "gcpvp": 3, "gcpvq": 2, "gcpyp": 2, "gcqd5": 2, "gcqzw": 1, "gcrb9": 1, "gcrcd": 2, "gcrjh": 1, "gctvm": 1, "gcu7g": 1, "gcudg": 3, "gcuem": 1, "gcuew": 1, "gcuey": 1, "gcuj7": 1, "gcuk4": 1, "gcuk5": 1, "gcupt": 1, "gcuru": 3, "gcusd": 1, "gcusn": 1, "gcusq": 1, "gcut3": 1, "gcuu3": 1, "gcuu9": 1, "gcuue": 4, "gcuv8": 1, "gcuvd": 12, "gcuve": 2, "gcuvg": 2, "gcuvm": 1, "gcuvr": 4, "gcuvs": 1, "gcuvt": 6, "gcuvu": 4, "gcuvv": 6, "gcuvw": 11, "gcuvx": 11, "gcuvy": 91, "gcuvz": 595, "gcuw5": 1, "gcuw6": 2, "gcuwp": 1, "gcuwx": 3, "gcuxc": 1, "gcuxe": 1, "gcuy1": 3, "gcuy2": 1, "gcuy4": 2, "gcuy5": 1, "gcuyh": 3, "gcuym": 1, "gcuyp": 2, "gcuyx": 1, "gcuz1": 1, "gcuzd": 1, "gcve1": 4, "gcvj2": 1, "gcvj3": 2, "gcvj6": 1, "gcvj7": 6, "gcvj8": 5, "gcvj9": 1, "gcvjb": 5, "gcvjc": 4, "gcvjd": 1, "gcvje": 1, "gcvjh": 1, "gcvjm": 1, "gcvmz": 1, "gcvn1": 1, "gcvn7": 1, "gcvnj": 1, "gcvnw": 1, "gcvpn": 1, "gcvpt": 1, "gcvpv": 1, "gcvq9": 1, "gcvqd": 2, "gcvw7": 1, "gcvwf": 1, "gcvwq": 14, "gcvwr": 2, "gcvx1": 1, "gcvy2": 1, "gcvy4": 1, "gcw1f": 1, "gcw27": 11, "gcw2h": 1, "gcwcw": 1, "gcwe4": 1, "gcwyh": 1, "gcwzr": 1, "gcx4z": 1, "gcx9z": 1, "gcxsw": 1, "gcy5t": 1, "gcybz": 1, "gcynf": 1, "gcynw": 1, "gcypb": 1, "gf4sq": 1, "gf4vc": 1, "gf5c9": 1, "gf5mz": 1, "gf5w4": 1, "gfh10": 1, "gfh77": 1, "gfh7h": 2, "gfh7n": 1, "gfhcw": 1, "gfhd2": 1, "gfhd4": 1, "gfhgq": 1, "gfhkq": 7, "gfj8c": 1, "gfj8p": 1, "gfjcn": 1, "gfjqn": 1, "gfkt5": 1, "gfm14": 1, "gfn03": 1, "gfn1t": 1, "gfnmp": 2, "gfnmq": 1, "gfnt0": 1, "gfq84": 1, "gpzzz": 1, "kekj9": 1, "r3gx2": 1, "snbyp": 1, "sp3e3": 1, "spc06": 1, "spyke": 1, "spzbx": 2, "spzcp": 2, "sr2yk": 2, "srb0b": 3, "srbj4": 1, "srd1e": 1, "sw6p3": 1, "swbfc": 1, "thrr3": 1, "u02w1": 1, "u04hq": 1, "u09tu": 1, "u09vf": 1, "u09wj": 13, "u0nd9": 1, "u10dv": 5, "u10j8": 1, "u10sp": 1, "u155k": 1, "u337n": 1, "u33db": 1, "u6sce": 1, "u8c56": 2, "u9fvg": 1, "uc09x": 1, "w21zs": 1, "w21zv": 1, "w283u": 1, "w4rw2": 1}