{"gcpum": 1, "qr6rw": 1, "swed8": 1, "swev8": 1, "swevy": 1, "swfcb": 2, "swg69": 1, "swg82": 1, "swgen": 1, "swkvz": 1, "swkxq": 1, "swkxv": 1, "swkxw": 2, "swkxx": 1, "swkxy": 10, "swkxz": 2, "swkyt": 1, "swkzm": 4, "swkzs": 1, "swmjf": 2, "sws1e": 1, "sws37": 1, "sws39": 1, "sws3p": 2, "sws4u": 2, "sws4v": 1, "sws5t": 2, "sws6k": 1, "sws8j": 1, "sws8k": 1, "sws8m": 4, "sws8n": 6, "sws8p": 4, "sws8q": 95, "sws8r": 4, "sws8u": 1, "sws8v": 1, "sws8w": 8, "sws94": 3, "swsb3": 1, "swsb7": 1, "swsbh": 1, "swsbk": 1, "swsww": 1, "swt16": 1, "swtcw": 1, "swtft": 1, "swtwz": 1, "swugu": 1, "sx4u2": 1, "sxj26": 1, "sxjx2": 1, "sxjxu": 4, "sxk97": 5, "sxk9h": 2, "sxk9v": 1, "sxnrw": 11, "sxp75": 3, "sxpkn": 1, "u1hv1": 1, "ucftp": 1}