{"dp3wm": 1, "f0pcx": 1, "swe6x": 2, "swed8": 1, "swg69": 1, "swkym": 1, "sws16": 1, "sws68": 1, "swtcf": 1, "sx510": 1, "sx5nd": 1, "sx5w3": 1, "sx7sf": 1, "sxh53": 1, "sxhsg": 1, "sxk35": 1, "sxk3j": 1, "sxk3p": 3, "sxk3q": 1, "sxk6j": 1, "sxk6q": 1, "sxk6x": 1, "sxk7h": 1, "sxk8v": 1, "sxk90": 1, "sxk91": 1, "sxk92": 2, "sxk93": 2, "sxk96": 15, "sxk97": 27, "sxk98": 1, "sxk99": 12, "sxk9c": 4, "sxk9d": 92, "sxk9e": 3, "sxk9g": 2, "sxk9j": 1, "sxk9k": 2, "sxk9s": 4, "sxk9t": 4, "sxk9u": 1, "sxk9v": 5, "sxkc3": 1, "sxkdk": 1, "sxkdq": 1, "sxnzf": 1, "sxpfc": 1, "u0w2b": 1, "u4kn8": 1}