{"6mc5n": 1, "dr5re": 1, "dr5rw": 1, "sx4kv": 1, "t9yk4": 1, "tdn8e": 1, "tdr1u": 1, "te7u6": 5, "tek92": 1, "tepen": 1, "tepfc": 2, "tewz2": 2, "tf346": 1, "tfcmf": 2, "tsjcw": 1, "tsph3": 1, "ttnfk": 1, "ttnfv": 1, "ttqwd": 1, "ttrkx": 1, "ttwk4": 1, "tu6zy": 1, "tu6zz": 3, "tu7p8": 1, "tu7p9": 2, "tu7pb": 7, "tu7pc": 4, "tu7qc": 1, "tuc88": 1, "tud2g": 1, "tudbn": 1, "tudbp": 2, "tue00": 96, "tue02": 1, "tue03": 16, "tuf2q": 2, "tunb6": 1, "tv05w": 1, "tv0xs": 1, "w21z7": 2, "w2839": 1, "wh0qc": 1}