{"6dkvg": 1, "6gjqm": 1, "6gwzr": 1, "6gyf4": 1, "6utsm": 1, "7h2y8": 1, "7nx4v": 1, "9g3w8": 11, "9q5c2": 1, "9q5ct": 2, "9q5fr": 1, "9q8yy": 1, "9qce7": 1, "9qdc4": 2, "9qh06": 1, "9qh1t": 1, "9qh4h": 9, "9t945": 2, "9t9p7": 33, "9tbq3": 1, "9tbqt": 1, "9v6kp": 1, "9v7bx": 1, "9xsqv": 1, "c28ry": 1, "d71qh": 2, "de60c": 1, "djn1u": 1, "djq58": 1, "dp3wb": 1, "dpxuq": 1, "dq6jk": 1, "dq8vu": 1, "dqcjq": 1, "dr1sb": 1, "dr4e3": 1, "dr5nw": 1, "dr5r8": 3, "dr5re": 3, "dr5rm": 1, "dr5rt": 1, "dr5ru": 1, "drt2y": 1, "dry03": 1, "ezjmg": 1, "ezjmu": 1, "gc7x9": 1, "gcpuk": 1, "gcpvk": 1, "gcqey": 1, "gcqy1": 1, "gcw2j": 1, "gcw2q": 1, "geejs": 1, "rjpfd": 1, "sggch": 1, "sncj2": 2, "spey4": 1, "spfb0": 1, "spv0k": 1, "spv0w": 1, "sqdtr": 1, "srb10": 1, "srb8b": 1, "srcyu": 1, "srsfe": 1, "sw6p3": 1, "sx25g": 1, "tdr1v": 1, "tepff": 8, "tkb49": 1, "tuvz4": 1, "u09tu": 1, "u09tv": 3, "u0fb5": 1, "u0hzv": 1, "u0mf5": 1, "u0mqs": 1, "u0p0u": 1, "u0qj9": 2, "u0rnx": 1, "u0rwe": 1, "u0t94": 1, "u0tyy": 1, "u0uz9": 1, "u0v37": 1, "u0v92": 1, "u0vhj": 1, "u0vqc": 1, "u0vqk": 2, "u0vs7": 1, "u0vu7": 6, "u0vue": 1, "u0vug": 8, "u0vur": 1, "u0vvx": 1, "u0wp7": 2, "u0wt2": 6, "u0wt7": 1, "u0wt8": 3, "u0wt9": 1, "u0wtt": 1, "u0wx9": 3, "u0xdx": 1, "u0y06": 1, "u0y18": 2, "u0y1e": 1, "u0y5c": 3, "u0y5k": 1, "u0y5s": 1, "u0y5u": 1, "u0y7z": 1, "u0yh9": 1, "u0yhb": 1, "u0yhd": 1, "u0yhe": 7, "u0yhq": 1, "u0yhu": 9, "u0yhv": 1, "u0yj5": 7, "u0yjb": 1, "u0yje": 1, "u0yjh": 6, "u0yjj": 296, "u0yjk": 2, "u0yjm": 1, "u0yjn": 15, "u0yjp": 2, "u0yjs": 1, "u0yjt": 1, "u0yju": 2, "u0yku": 1, "u0ym3": 1, "u0ym9": 1, "u0ymh": 1, "u0ymm": 1, "u0ynj": 1, "u0ynq": 1, "u0yrt": 2, "u0ys2": 2, "u0yt8": 2, "u0yx3": 1, "u0yzs": 2, "u0z82": 1, "u0zck": 2, "u0zf4": 1, "u0zvc": 1, "u10j8": 1, "u135r": 1, "u1516": 1, "u173z": 6, "u1hbu": 1, "u1hcv": 1, "u1hcy": 3, "u1hfq": 1, "u1hg2": 1, "u1hg6": 2, "u1hsj": 1, "u1j09": 1, "u1j0g": 1, "u1j5b": 1, "u1j5d": 1, "u1j5u": 1, "u1j9q": 1, "u1jj5": 1, "u1jt8": 1, "u1msw": 1, "u1n3j": 2, "u1nck": 1, "u1p45": 2, "u1p9g": 1, "u1q9x": 1, "u1qcv": 1, "u1qf5": 1, "u1r3n": 1, "u1r3r": 1, "u1t1d": 1, "u1x05": 1, "u1x0d": 1, "u1x0e": 2, "u1x1s": 1, "u1zpr": 1, "u20f2": 1, "u23nr": 1, "u281z": 4, "u28j7": 1, "u28np": 1, "u2edk": 2, "u2fkb": 1, "u2fm0": 1, "u30u1": 4, "u33d9": 2, "u33db": 4, "u33dc": 1, "u3buw": 1, "u8vrx": 1, "w4rqn": 1, "ws0e9": 1, "wtw3e": 2, "xn0x1": 1, "zgw0r": 1}