{"dng18": 1, "dqcjq": 1, "gbwrz": 1, "gcj2x": 3, "gcj88": 1, "gcjsx": 1, "gcjuj": 1, "gcnge": 2, "gcpef": 1, "gcpkd": 1, "gcpke": 4, "gcpne": 1, "gcpsx": 1, "gcpug": 2, "gcpuz": 2, "gcpv0": 1, "gcpv8": 1, "gcpxn": 1, "gcpy5": 1, "gcpyx": 1, "gcqpu": 2, "gcrj9": 1, "sv8wn": 1, "u105u": 2, "u10h6": 1, "u10h9": 1, "u1214": 2, "u61y9": 1, "u6282": 1, "u66gb": 1, "u6dcq": 1, "u6e9z": 1, "u6fej": 1, "u6hyj": 1, "u6jph": 1, "u6s2s": 1, "u6s9r": 1, "u6sc2": 1, "u6sc3": 1, "u6sc5": 1, "u6sc6": 4, "u6sc7": 1, "u6sc8": 85, "u6sc9": 1, "u6scd": 2, "u6sce": 2, "u6sct": 1, "u6sd7": 1, "u6sf4": 2, "u7d8z": 1, "u7xv1": 1, "xn0m5": 1}