{"u6zb0": 2, "ud9p4": 1, "ud9qu": 1, "ud9qx": 2, "ud9w6": 1, "ud9w7": 3, "ud9w8": 1, "ud9w9": 2, "ud9we": 5, "ud9wf": 1, "ud9wk": 2, "ud9wm": 5, "ud9wq": 2, "ud9wr": 6, "ud9ws": 14, "ud9wt": 3, "ud9wu": 2, "ud9wv": 2, "ud9ww": 7, "ud9wx": 2, "ud9wy": 1, "ud9wz": 1, "ud9xj": 2, "ud9xk": 2, "ud9xn": 3, "ud9yb": 3, "ud9yc": 2, "ud9yd": 1, "ud9yf": 1, "ud9ys": 1, "ud9yv": 1, "ud9z7": 1, "udbvk": 1, "udcmz": 1, "uddnb": 1, "uddp4": 1, "uddp5": 1, "uddr8": 1, "udfb6": 1, "udurt": 1, "ue2u6": 1, "ue7tr": 1}