{"wvutt": 1, "wypgv": 1, "wypjs": 1, "wypmf": 1, "wypxn": 1, "wyr3r": 1, "wyrfe": 2, "xn0j7": 3, "xn0je": 2, "xn0jk": 6, "xn0kd": 1, "xn0m5": 1, "xn0m7": 8, "xn0mb": 1, "xn0me": 2, "xn0mf": 2, "xn0mg": 1, "xn0mh": 1, "xn0mt": 1, "xn0n1": 1, "xn0n5": 1, "xn0n7": 1, "xn0ne": 1, "xn0ng": 1, "xn0nh": 4, "xn0nj": 3, "xn0nk": 4, "xn0nm": 29, "xn0np": 4, "xn0nq": 3, "xn0ns": 7, "xn0nt": 8, "xn0nv": 1, "xn0pk": 3, "xn0px": 1, "xn0q1": 1, "xn0q3": 3, "xn0q4": 1, "xn0qh": 4, "xn0s6": 1, "xn0t6": 1, "xn0x1": 1, "xn200": 1, "xn20u": 1, "xn2v5": 1, "xn6nd": 1, "xnd22": 1, "xnu1n": 1}