{"r64cq": 1, "sp9p9": 1, "sp9pc": 1, "wsmgt": 1, "wyptd": 1, "wypvb": 1, "xjbqt": 1, "xn05v": 1, "xn07q": 1, "xn0e9": 1, "xn0eb": 1, "xn0hb": 1, "xn0j4": 1, "xn0jk": 1, "xn0jx": 1, "xn0k3": 1, "xn0ke": 1, "xn0kf": 1, "xn0kg": 3, "xn0kz": 1, "xn0m4": 1, "xn0m5": 14, "xn0m7": 3, "xn0m9": 5, "xn0mb": 1, "xn0md": 1, "xn0me": 2, "xn0mh": 4, "xn0mj": 1, "xn0mq": 2, "xn0mr": 6, "xn0mu": 1, "xn0mw": 1, "xn0q5": 1, "xn0s0": 1, "xn0s2": 2, "xn0s4": 3, "xn0s6": 2, "xn0s7": 2, "xn0s8": 1, "xn0s9": 1, "xn0sb": 1, "xn0sc": 1, "xn0sd": 1, "xn0sf": 5, "xn0sv": 4, "xn0t1": 7, "xn0t2": 11, "xn0t3": 154, "xn0t4": 4, "xn0t5": 1, "xn0t6": 21, "xn0t8": 3, "xn0t9": 5, "xn0td": 9, "xn0te": 2, "xn0tk": 1, "xn0u8": 1, "xn0vc": 1, "xn0w1": 3, "xn0w3": 4, "xn0wc": 2, "xn0x0": 2, "xn0x1": 5, "xn0x3": 1, "xn171": 1, "xn1jd": 1, "xn1rs": 1, "xn76e": 1, "xn7vg": 1, "xndg3": 1}