{"wvuxp": 1, "xn0wv": 1, "xn1mf": 1, "xn1q3": 1, "xn1q7": 1, "xn1qk": 2, "xn1qn": 1, "xn1qq": 1, "xn1qr": 2, "xn1qv": 1, "xn1qw": 1, "xn1qy": 1, "xn1qz": 5, "xn1rg": 3, "xn1rj": 3, "xn1rk": 1, "xn1rm": 1, "xn1rp": 3, "xn1rx": 1, "xn1tt": 2, "xn1tw": 2, "xn1ty": 3, "xn1vq": 2, "xn1w3": 9, "xn1w4": 4, "xn1w5": 1, "xn1w8": 7, "xn1w9": 70, "xn1wb": 3, "xn1wc": 18, "xn1wd": 28, "xn1wg": 1, "xn1wh": 2, "xn1wk": 1, "xn1wq": 1, "xn1x0": 2, "xn1x1": 3, "xn1x2": 2, "xn1x3": 1, "xn1x6": 1, "xn1x9": 1, "xn1xb": 1, "xn1xq": 1, "xn2bv": 1, "xn31h": 1, "xn31r": 1, "xn324": 4, "xn325": 2, "xn326": 1, "xn32e": 1, "xn32h": 1, "xn32n": 1, "xn32p": 1, "xn32r": 1, "xn32t": 1, "xn32w": 1, "xn365": 1, "xn390": 1, "xn3b2": 1, "xn4rz": 1, "xn4xz": 1, "xn684": 1, "xn776": 1}