{"xn1yn": 2, "xn39x": 1, "xn3vw": 1, "xn4x0": 1, "xn4yg": 1, "xn63y": 1, "xn654": 1, "xn66x": 2, "xn66z": 42, "xn67g": 2, "xn67n": 6, "xn67p": 3, "xn67r": 2, "xn67t": 1, "xn685": 1, "xn693": 1, "xn69w": 1, "xn6bf": 1, "xn6cn": 2, "xn6d8": 3, "xn6d9": 5, "xn6db": 18, "xn6dc": 3, "xn6dd": 2, "xn6de": 1, "xn6df": 7, "xn6dg": 3, "xn6e0": 3, "xn6e5": 3, "xn6f3": 1, "xn6f8": 1, "xn6fs": 12, "xn6fw": 2, "xn6hv": 2, "xn6hx": 1, "xn6hy": 1, "xn6hz": 9, "xn6jd": 1, "xn6jf": 1, "xn6jj": 1, "xn6jk": 1, "xn6jm": 1, "xn6jn": 2, "xn6jr": 1, "xn6k3": 5, "xn6k5": 2, "xn6k7": 1, "xn6k8": 1, "xn6kf": 1, "xn6kt": 1, "xn6kw": 1, "xn6m2": 4, "xn6m3": 3, "xn6mf": 1, "xn6mh": 2, "xn6n4": 1, "xn6n5": 1, "xn6n6": 1, "xn6nd": 2, "xn6r5": 1, "xn6ym": 1, "xn71e": 1, "xn71v": 1, "xn739": 1, "xn73g": 1, "xn742": 1, "xn746": 1, "xn748": 1, "xn74g": 1, "xn74u": 1, "xn754": 1, "xn75t": 1, "xn75w": 2, "xn762": 1, "xn76d": 1, "xn76u": 1, "xn774": 1, "xn77c": 1, "xn77g": 1, "xn7e1": 1, "xn7e4": 1, "xn7k8": 1, "xn7kd": 2, "xn7nd": 1}